build/__init__.py
wexample_workspaces/__init__.py
wexample_workspaces-0.0.3.dist-info/METADATA
wexample_workspaces-0.0.3.dist-info/WHEEL
wexample_workspaces-0.0.3.dist-info/__init__.py
wexample_workspaces-0.0.3.dist-info/top_level.txt
wexample_workspaces-0.0.3.dist-info/RECORD
